wztools/__init__.py
wztools/datalake/datalake.py
wztools/utils/__init__.py
wztools/utils/command.py
wztools/utils/debug_utils.py
wztools/utils/load_utils.py
wztools/utils/logger.py
wztools/utils/mat_utils.py
wztools/utils/spatial_utils.py
wztools/utils/time_utils.py
wztools-2026.1.6.dist-info/METADATA
wztools-2026.1.6.dist-info/WHEEL
wztools-2026.1.6.dist-info/top_level.txt
wztools-2026.1.6.dist-info/RECORD
