Metadata-Version: 2.4
Name: wztools
Version: 2026.1.6
Summary: 个人用工具库
Requires-Python: >=3.11
Requires-Dist: rich
